Workbook
Name NativeTimeline_Order_Date: #N/A
Name Slicer_Category: #N/A
Name Slicer_Region: #N/A
Name Slicer_Segment: #N/A

Sheet Pivot Sales By region
A3: Row Labels | B3: Sum of Sales
A4: East | B4: 1274916.7
A5: North | B5: 1268981.1
A6: South | B6: 1250820.4
A7: West | B7: 1275743.3
A8: Grand Total | B8: 5070461.5

Sheet Profit by category
A3: Row Labels | B3: Sum of Profit
A4: Furniture | B4: 243115.88
A5: Office Supplies | B5: 240901.96
A6: Technology | B6: 248427.49
A7: Grand Total | B7: 732445.33

Sheet Sales By segment
A3: Row Labels | B3: Sum of Sales
A4: Consumer | B4: 1824074.1
A5: Corporate | B5: 1353125.1
A6: Home Office | B6: 1893262.3
A7: Grand Total | B7: 5070461.5

Sheet Sales By Category And Region
A3: Sum of Sales | B3: Column Labels
A4: Row Labels | B4: Furniture | C4: Office Supplies | D4: Technology | E4: Grand Total
A5: East | B5: 443661.21 | C5: 422199 | D5: 409056.44 | E5: 1274916.7
A6: North | B6: 422184.2 | C6: 409003.12 | D6: 437793.75 | E6: 1268981.1
A7: South | B7: 419617.02 | C7: 415003.33 | D7: 416200.09 | E7: 1250820.4
A8: West | B8: 412552.97 | C8: 438814.13 | D8: 424376.22 | E8: 1275743.3
A9: Grand Total | B9: 1698015.4 | C9: 1685019.6 | D9: 1687426.5 | E9: 5070461.5

Sheet Slicer

Sheet DashBoard
O1: Global Superstore Sales Performance Dashboard
A3: TOTAL SALES | D3: TOTAL PROFIT | G3: TOTAL ORDERS | J3: AVERAGE SALES
A4: ='Pivot Sales By region'!B8 -> 5070461.5 | D4: ='Profit by category'!B7 -> 732445.33 | G4: =Sheet1!A4 -> 5000 | J4: =A4/G4 -> 1014.0923
S5: FILTERS
U52: Created by UGBE JULIET Excel Dashboard Project | 2026

Sheet Monthly Sales
A3: Row Labels | B3: Sum of Sales
A4: 2023
A5: Jan | B5: 226060.54
A6: Feb | B6: 165777.43
A7: Mar | B7: 231616.84
A8: Apr | B8: 206254.44
A9: May | B9: 223206.82
A10: Jun | B10: 209297.65
A11: Jul | B11: 230037.43
A12: Aug | B12: 247971.56
A13: Sep | B13: 228170.01
A14: Oct | B14: 214298.53
A15: Nov | B15: 199612.2
A16: Dec | B16: 195492.59
A17: 2024
A18: Jan | B18: 207800.83
A19: Feb | B19: 177366.49
A20: Mar | B20: 190597.27
A21: Apr | B21: 206199.99
A22: May | B22: 200682.05
A23: Jun | B23: 228381.75
A24: Jul | B24: 213057.89
A25: Aug | B25: 209250.04
A26: Sep | B26: 240149.05
A27: Oct | B27: 206275.23
A28: Nov | B28: 211938.73
A29: Dec | B29: 200966.12
A30: Grand Total | B30: 5070461.5

Sheet Top 10 
A3: Row Labels | B3: Sum of Sales
A4: Customer 14 | B4: 66350.32
A5: Customer 20 | B5: 66978.57
A6: Customer 30 | B6: 71333.9
A7: Customer 38 | B7: 63467.27
A8: Customer 43 | B8: 71237.64
A9: Customer 48 | B9: 64379.43
A10: Customer 51 | B10: 63626.82
A11: Customer 55 | B11: 67977.05
A12: Customer 57 | B12: 79774
A13: Customer 66 | B13: 64268.07
A14: Grand Total | B14: 679393.07

Sheet Sheet1
A3: Count of Order ID
A4: 5000

Sheet Orders
A1: Order ID | B1: Order Date | C1: Ship Date | D1: Customer ID | E1: Customer Name | F1: Segment | G1: Region | H1: State | I1: City | J1: Product ID | K1: Category | L1: Sub-Category | M1: Product Name | N1: Sales | O1: Quantity | P1: Discount | Q1: Profit | R1: YEAR | S1: MONTH | T1: PROFIT MARGIN(%) | U1: Profit Status | V1: ORDER SIZE
A2: O00001 | B2: 45517 | C2: 45524 | D2: C039 | E2: Customer 39 | F2: Corporate | G2: South | H2: Rivers | I2: Port Harcourt | J2: P019 | K2: Office Supplies | L2: Binders | M2: Binders Model 4 | N2: 1286.15 | O2: 2 | P2: 0.05 | Q2: 270.09 | R2: =YEAR(B2) -> 2024 | S2: =TEXT(B2,"mmmm") -> August | T2: =Q2/N2 -> 0.20999883 | U2: =IF(Q2>0,"Profit","Loss") -> Profit | V2: =IF(N2>1000,"Large Order","Small Order") -> Large Order
A3: O00002 | B3: 45486 | C3: 45490 | D3: C011 | E3: Customer 11 | F3: Home Office | G3: South | H3: Rivers | I3: Port Harcourt | J3: P027 | K3: Technology | L3: Accessories | M3: Accessories Model 2 | N3: 812.76 | O3: 5 | P3: 0.2 | Q3: 73.15 | R3: =YEAR(B3) -> 2024 | S3: =TEXT(B3,"mmmm") -> July | T3: =Q3/N3 -> 0.090001969 | U3: =IF(Q3>0,"Profit","Loss") -> Profit | V3: =IF(N3>1000,"Large Order","Small Order") -> Small Order
A4: O00003 | B4: 45048 | C4: 45049 | D4: C072 | E4: Customer 72 | F4: Corporate | G4: North | H4: Kaduna | I4: Kaduna | J4: P010 | K4: Furniture | L4: Tables | M4: Tables Model 5 | N4: 1492.15 | O4: 1 | P4: 0 | Q4: 373.04 | R4: =YEAR(B4) -> 2023 | S4: =TEXT(B4,"mmmm") -> May | T4: =Q4/N4 -> 0.25000168 | U4: =IF(Q4>0,"Profit","Loss") -> Profit | V4: =IF(N4>1000,"Large Order","Small Order") -> Large Order
A5: O00004 | B5: 45379 | C5: 45386 | D5: C070 | E5: Customer 70 | F5: Consumer | G5: East | H5: Enugu | I5: Enugu | J5: P029 | K5: Technology | L5: Accessories | M5: Accessories Model 4 | N5: 1418.3 | O5: 4 | P5: 0.3 | Q5: 14.18 | R5: =YEAR(B5) -> 2024 | S5: =TEXT(B5,"mmmm") -> March | T5: =Q5/N5 -> 0.0099978848 | U5: =IF(Q5>0,"Profit","Loss") -> Profit | V5: =IF(N5>1000,"Large Order","Small Order") -> Large Order
A6: O00005 | B6: 45475 | C6: 45479 | D6: C050 | E6: Customer 50 | F6: Home Office | G6: North | H6: Kaduna | I6: Kaduna | J6: P029 | K6: Technology | L6: Accessories | M6: Accessories Model 4 | N6: 1382.59 | O6: 4 | P6: 0 | Q6: 345.65 | R6: =YEAR(B6) -> 2024 | S6: =TEXT(B6,"mmmm") -> July | T6: =Q6/N6 -> 0.25000181 | U6: =IF(Q6>0,"Profit","Loss") -> Profit | V6: =IF(N6>1000,"Large Order","Small Order") -> Large Order
A7: O00006 | B7: 45395 | C7: 45402 | D7: C018 | E7: Customer 18 | F7: Corporate | G7: North | H7: Kaduna | I7: Kaduna | J7: P027 | K7: Technology | L7: Accessories | M7: Accessories Model 2 | N7: 1449.53 | O7: 8 | P7: 0.3 | Q7: 14.5 | R7: =YEAR(B7) -> 2024 | S7: =TEXT(B7,"mmmm") -> April | T7: =Q7/N7 -> 0.010003242 | U7: =IF(Q7>0,"Profit","Loss") -> Profit | V7: =IF(N7>1000,"Large Order","Small Order") -> Large Order
A8: O00007 | B8: 45274 | C8: 45277 | D8: C079 | E8: Customer 79 | F8: Consumer | G8: South | H8: Rivers | I8: Port Harcourt | J8: P020 | K8: Office Supplies | L8: Binders | M8: Binders Model 5 | N8: 984.5 | O8: 3 | P8: 0.1 | Q8: 167.36 | R8: =YEAR(B8) -> 2023 | S8: =TEXT(B8,"mmmm") -> December | T8: =Q8/N8 -> 0.16999492 | U8: =IF(Q8>0,"Profit","Loss") -> Profit | V8: =IF(N8>1000,"Large Order","Small Order") -> Small Order
A9: O00008 | B9: 45068 | C9: 45072 | D9: C068 | E9: Customer 68 | F9: Home Office | G9: North | H9: Kaduna | I9: Kaduna | J9: P009 | K9: Furniture | L9: Tables | M9: Tables Model 4 | N9: 1742.43 | O9: 5 | P9: 0 | Q9: 435.61 | R9: =YEAR(B9) -> 2023 | S9: =TEXT(B9,"mmmm") -> May | T9: =Q9/N9 -> 0.25000143 | U9: =IF(Q9>0,"Profit","Loss") -> Profit | V9: =IF(N9>1000,"Large Order","Small Order") -> Large Order
A10: O00009 | B10: 45207 | C10: 45213 | D10: C045 | E10: Customer 45 | F10: Consumer | G10: East | H10: Enugu | I10: Enugu | J10: P003 | K10: Furniture | L10: Chairs | M10: Chairs Model 3 | N10: 984.71 | O10: 10 | P10: 0 | Q10: 246.18 | R10: =YEAR(B10) -> 2023 | S10: =TEXT(B10,"mmmm") -> October | T10: =Q10/N10 -> 0.25000254 | U10: =IF(Q10>0,"Profit","Loss") -> Profit | V10: =IF(N10>1000,"Large Order","Small Order") -> Small Order
A11: O00010 | B11: 45269 | C11: 45273 | D11: C089 | E11: Customer 89 | F11: Consumer | G11: West | H11: Lagos | I11: Ikeja | J11: P027 | K11: Technology | L11: Accessories | M11: Accessories Model 2 | N11: 786.78 | O11: 8 | P11: 0.3 | Q11: 7.87 | R11: =YEAR(B11) -> 2023 | S11: =TEXT(B11,"mmmm") -> December | T11: =Q11/N11 -> 0.010002796 | U11: =IF(Q11>0,"Profit","Loss") -> Profit | V11: =IF(N11>1000,"Large Order","Small Order") -> Small Order
A12: O00011 | B12: 44940 | C12: 44944 | D12: C063 | E12: Customer 63 | F12: Corporate | G12: East | H12: Enugu | I12: Enugu | J12: P028 | K12: Technology | L12: Accessories | M12: Accessories Model 3 | N12: 1286.49 | O12: 9 | P12: 0.2 | Q12: 115.78 | R12: =YEAR(B12) -> 2023 | S12: =TEXT(B12,"mmmm") -> January | T12: =Q12/N12 -> 0.089996813 | U12: =IF(Q12>0,"Profit","Loss") -> Profit | V12: =IF(N12>1000,"Large Order","Small Order") -> Large Order
A13: O00012 | B13: 45333 | C13: 45334 | D13: C079 | E13: Customer 79 | F13: Consumer | G13: North | H13: Kaduna | I13: Kaduna | J13: P024 | K13: Technology | L13: Phones | M13: Phones Model 4 | N13: 884.88 | O13: 8 | P13: 0.2 | Q13: 79.64 | R13: =YEAR(B13) -> 2024 | S13: =TEXT(B13,"mmmm") -> February | T13: =Q13/N13 -> 0.090000904 | U13: =IF(Q13>0,"Profit","Loss") -> Profit | V13: =IF(N13>1000,"Large Order","Small Order") -> Small Order
... A15: O00014 | B15: 45475 | C15: 45477 | D15: C020 | E15: Customer 20 | F15: Corporate | G15: South | H15: Rivers | I15: Port Harcourt | J15: P025 | K15: Technology | L15: Phones | M15: Phones Model 5 | N15: 697.3 | O15: 8 | P15: 0.2 | Q15: 62.76 | R15: =YEAR(B15) -> 2024 | S15: =TEXT(B15,"mmmm") -> July | T15: =Q15/N15 -> 0.090004302 | U15: =IF(Q15>0,"Profit","Loss") -> Profit | V15: =IF(N15>1000,"Large Order","Small Order") -> Small Order
A16: O00015 | B16: 45231 | C16: 45237 | D16: C099 | E16: Customer 99 | F16: Home Office | G16: West | H16: Lagos | I16: Ikeja | J16: P029 | K16: Technology | L16: Accessories | M16: Accessories Model 4 | N16: 686.06 | O16: 1 | P16: 0.05 | Q16: 144.07 | R16: =YEAR(B16) -> 2023 | S16: =TEXT(B16,"mmmm") -> November | T16: =Q16/N16 -> 0.20999621 | U16: =IF(Q16>0,"Profit","Loss") -> Profit | V16: =IF(N16>1000,"Large Order","Small Order") -> Small Order | AD16: =ISNUMBER(N2) -> TRUE
A17: O00016 | B17: 44974 | C17: 44979 | D17: C098 | E17: Customer 98 | F17: Corporate | G17: East | H17: Enugu | I17: Enugu | J17: P001 | K17: Furniture | L17: Chairs | M17: Chairs Model 1 | N17: 243.2 | O17: 2 | P17: 0.1 | Q17: 41.34 | R17: =YEAR(B17) -> 2023 | S17: =TEXT(B17,"mmmm") -> February | T17: =Q17/N17 -> 0.16998355 | U17: =IF(Q17>0,"Profit","Loss") -> Profit | V17: =IF(N17>1000,"Large Order","Small Order") -> Small Order
A18: O00017 | B18: 45655 | C18: 45662 | D18: C027 | E18: Customer 27 | F18: Consumer | G18: East | H18: Enugu | I18: Enugu | J18: P010 | K18: Furniture | L18: Tables | M18: Tables Model 5 | N18: 1808.96 | O18: 8 | P18: 0.2 | Q18: 162.81 | R18: =YEAR(B18) -> 2024 | S18: =TEXT(B18,"mmmm") -> December | T18: =Q18/N18 -> 0.09000199 | U18: =IF(Q18>0,"Profit","Loss") -> Profit | V18: =IF(N18>1000,"Large Order","Small Order") -> Large Order
A19: O00018 | B19: 45087 | C19: 45089 | D19: C033 | E19: Customer 33 | F19: Consumer | G19: South | H19: Rivers | I19: Port Harcourt | J19: P017 | K19: Office Supplies | L19: Binders | M19: Binders Model 2 | N19: 827.57 | O19: 1 | P19: 0.1 | Q19: 140.69 | R19: =YEAR(B19) -> 2023 | S19: =TEXT(B19,"mmmm") -> June | T19: =Q19/N19 -> 0.17000375 | U19: =IF(Q19>0,"Profit","Loss") -> Profit | V19: =IF(N19>1000,"Large Order","Small Order") -> Small Order
A20: O00019 | B20: 45657 | C20: 45664 | D20: C056 | E20: Customer 56 | F20: Corporate | G20: West | H20: Lagos | I20: Ikeja | J20: P029 | K20: Technology | L20: Accessories | M20: Accessories Model 4 | N20: 722.01 | O20: 4 | P20: 0.1 | Q20: 122.74 | R20: =YEAR(B20) -> 2024 | S20: =TEXT(B20,"mmmm") -> December | T20: =Q20/N20 -> 0.16999765 | U20: =IF(Q20>0,"Profit","Loss") -> Profit | V20: =IF(N20>1000,"Large Order","Small Order") -> Small Order
A21: O00020 | B21: 45347 | C21: 45354 | D21: C001 | E21: Customer 1 | F21: Corporate | G21: West | H21: Lagos | I21: Ikeja | J21: P007 | K21: Furniture | L21: Tables | M21: Tables Model 2 | N21: 1711.05 | O21: 1 | P21: 0.05 | Q21: 359.32 | R21: =YEAR(B21) -> 2024 | S21: =TEXT(B21,"mmmm") -> February | T21: =Q21/N21 -> 0.20999971 | U21: =IF(Q21>0,"Profit","Loss") -> Profit | V21: =IF(N21>1000,"Large Order","Small Order") -> Large Order
A22: O00021 | B22: 45314 | C22: 45319 | D22: C002 | E22: Customer 2 | F22: Consumer | G22: West | H22: Lagos | I22: Ikeja | J22: P029 | K22: Technology | L22: Accessories | M22: Accessories Model 4 | N22: 804.97 | O22: 4 | P22: 0.2 | Q22: 72.45 | R22: =YEAR(B22) -> 2024 | S22: =TEXT(B22,"mmmm") -> January | T22: =Q22/N22 -> 0.090003354 | U22: =IF(Q22>0,"Profit","Loss") -> Profit | V22: =IF(N22>1000,"Large Order","Small Order") -> Small Order
A23: O00022 | B23: 45455 | C23: 45458 | D23: C063 | E23: Customer 63 | F23: Corporate | G23: South | H23: Rivers | I23: Port Harcourt | J23: P018 | K23: Office Supplies | L23: Binders | M23: Binders Model 3 | N23: 1775.04 | O23: 2 | P23: 0.3 | Q23: 17.75 | R23: =YEAR(B23) -> 2024 | S23: =TEXT(B23,"mmmm") -> June | T23: =Q23/N23 -> 0.0099997747 | U23: =IF(Q23>0,"Profit","Loss") -> Profit | V23: =IF(N23>1000,"Large Order","Small Order") -> Large Order
A24: O00023 | B24: 45400 | C24: 45401 | D24: C082 | E24: Customer 82 | F24: Consumer | G24: West | H24: Lagos | I24: Ikeja | J24: P017 | K24: Office Supplies | L24: Binders | M24: Binders Model 2 | N24: 1484.74 | O24: 7 | P24: 0.05 | Q24: 311.8 | R24: =YEAR(B24) -> 2024 | S24: =TEXT(B24,"mmmm") -> April | T24: =Q24/N24 -> 0.2100031 | U24: =IF(Q24>0,"Profit","Loss") -> Profit | V24: =IF(N24>1000,"Large Order","Small Order") -> Large Order
A25: O00024 | B25: 45274 | C25: 45279 | D25: C073 | E25: Customer 73 | F25: Consumer | G25: North | H25: Kaduna | I25: Kaduna | J25: P008 | K25: Furniture | L25: Tables | M25: Tables Model 3 | N25: 588.35 | O25: 4 | P25: 0.2 | Q25: 52.95 | R25: =YEAR(B25) -> 2023 | S25: =TEXT(B25,"mmmm") -> December | T25: =Q25/N25 -> 0.08999745 | U25: =IF(Q25>0,"Profit","Loss") -> Profit | V25: =IF(N25>1000,"Large Order","Small Order") -> Small Order
A26: O00025 | B26: 45042 | C26: 45047 | D26: C087 | E26: Customer 87 | F26: Home Office | G26: North | H26: Kaduna | I26: Kaduna | J26: P008 | K26: Furniture | L26: Tables | M26: Tables Model 3 | N26: 1321.08 | O26: 2 | P26: 0.3 | Q26: 13.21 | R26: =YEAR(B26) -> 2023 | S26: =TEXT(B26,"mmmm") -> April | T26: =Q26/N26 -> 0.0099993944 | U26: =IF(Q26>0,"Profit","Loss") -> Profit | V26: =IF(N26>1000,"Large Order","Small Order") -> Large Order
A27: O00026 | B27: 45566 | C27: 45568 | D27: C070 | E27: Customer 70 | F27: Consumer | G27: West | H27: Lagos | I27: Ikeja | J27: P001 | K27: Furniture | L27: Chairs | M27: Chairs Model 1 | N27: 525.84 | O27: 7 | P27: 0.3 | Q27: 5.26 | R27: =YEAR(B27) -> 2024 | S27: =TEXT(B27,"mmmm") -> October | T27: =Q27/N27 -> 0.010003043 | U27: =IF(Q27>0,"Profit","Loss") -> Profit | V27: =IF(N27>1000,"Large Order","Small Order") -> Small Order
A28: O00027 | B28: 45484 | C28: 45490 | D28: C030 | E28: Customer 30 | F28: Home Office | G28: West | H28: Lagos | I28: Ikeja | J28: P022 | K28: Technology | L28: Phones | M28: Phones Model 2 | N28: 670.47 | O28: 3 | P28: 0.1 | Q28: 113.98 | R28: =YEAR(B28) -> 2024 | S28: =TEXT(B28,"mmmm") -> July | T28: =Q28/N28 -> 0.17000015 | U28: =IF(Q28>0,"Profit","Loss") -> Profit | V28: =IF(N28>1000,"Large Order","Small Order") -> Small Order
... A5001: O05000 | B5001: 45210 | C5001: 45214 | D5001: C079 | E5001: Customer 79 | F5001: Consumer | G5001: East | H5001: Enugu | I5001: Enugu | J5001: P028 | K5001: Technology | L5001: Accessories | M5001: Accessories Model 3 | N5001: 1046.44 | O5001: 10 | P5001: 0.2 | Q5001: 94.18 | R5001: =YEAR(B5001) -> 2023 | S5001: =TEXT(B5001,"mmmm") -> October | T5001: =Q5001/N5001 -> 0.090000382 | U5001: =IF(Q5001>0,"Profit","Loss") -> Profit | V5001: =IF(N5001>1000,"Large Order","Small Order") -> Large Order

Sheet Customers
A1: Column1 | B1: Column2 | C1: Column3
A2: Customer ID | B2: Customer Name | C2: Segment
A3: C001 | B3: Customer 1 | C3: Corporate
A4: C002 | B4: Customer 2 | C4: Consumer
A5: C003 | B5: Customer 3 | C5: Corporate
A6: C004 | B6: Customer 4 | C6: Home Office
A7: C005 | B7: Customer 5 | C7: Consumer
A8: C006 | B8: Customer 6 | C8: Home Office
A9: C007 | B9: Customer 7 | C9: Corporate
A10: C008 | B10: Customer 8 | C10: Consumer
A11: C009 | B11: Customer 9 | C11: Corporate
A12: C010 | B12: Customer 10 | C12: Consumer
... A102: C100 | B102: Customer 100 | C102: Consumer

Sheet Products
A1: Product ID | B1: Category | C1: Sub-Category | D1: Product Name
A2: P001 | B2: Furniture | C2: Chairs | D2: Chairs Model 1
A3: P002 | B3: Furniture | C3: Chairs | D3: Chairs Model 2
A4: P003 | B4: Furniture | C4: Chairs | D4: Chairs Model 3
A5: P004 | B5: Furniture | C5: Chairs | D5: Chairs Model 4
A6: P005 | B6: Furniture | C6: Chairs | D6: Chairs Model 5
A7: P006 | B7: Furniture | C7: Tables | D7: Tables Model 1
A8: P007 | B8: Furniture | C8: Tables | D8: Tables Model 2
A9: P008 | B9: Furniture | C9: Tables | D9: Tables Model 3
A10: P009 | B10: Furniture | C10: Tables | D10: Tables Model 4
A11: P010 | B11: Furniture | C11: Tables | D11: Tables Model 5
A12: P011 | B12: Office Supplies | C12: Paper | D12: Paper Model 1
... A31: P030 | B31: Technology | C31: Accessories | D31: Accessories Model 5

Sheet Lookup pratice
A1: Product ID | B1: CATEGORY
A2: P001 | B2: =VLOOKUP(A2,Products!A$1:$D$31,2,FALSE) -> Furniture
A3: P008 | B3: =VLOOKUP(A3,Products!A$1:$D$31,2,FALSE) -> Furniture
A4: P015 | B4: =VLOOKUP(A4,Products!A$1:$D$31,2,FALSE) -> Office Supplies
A5: P022 | B5: =VLOOKUP(A5,Products!A$1:$D$31,2,FALSE) -> Technology
A6: P030 | B6: =VLOOKUP(A6,Products!A$1:$D$31,2,FALSE) -> Technology

Sheet Sumifs pratice
A1: Category | B1: Total Sales
A2: Furniture | B2: =SUMIFS(Orders!$N:$N,Orders!$K:$K,A2) -> 1698015.4
A3: Office Supplies | B3: =SUMIFS(Orders!$N:$N,Orders!$K:$K,A3) -> 1685019.6
A4: Technology | B4: =SUMIFS(Orders!$N:$N,Orders!$K:$K,A4) -> 1687426.5

Sheet Countif
A1: Furniture | B1: =COUNTIFS(Orders!$K:$K,"Furniture") -> 1664
A2: Office Supplies | B2: =COUNTIFS(Orders!$K:$K,"Office Supplies") -> 1648
A3: Technology | B3: =COUNTIFS(Orders!$K:$K,"Technology") -> 1688
A4: West | B4: =COUNTIFS(Orders!$G:$G,"West") -> 1261
